---
title: 字符串
date: 2019-03-27 15:49:53
categories:
  - Java
tags: 
	- Java
---

# String #

**String不变性**

- String是final类，不能被继承。
- 其实是通过char数组来保存字符串的
- 所有操作都不是在原有的字符串上进行的，而是重新生成了一个新的字符串对象。也就是说进行这些操作后，最原始的字符串并没有被改变。

		public final class String implements java.io.Serializable, Comparable<String>, CharSequence {}

## String对象绑定引用 ##

**String str="hello world"**

- 将String对象跟引用绑定
- JVM执行引擎先在运行时常量池查找是否存在相同的字面常量
	- 如果存在，则直接将引用指向已经存在的字面常量；
	- 否则在运行时常量池开辟一个空间来存储该字面常量，并将引用指向该字面常量。

**String str=new String("hello world")**

- new关键字生成对象是在堆区进行的,创建出的一定是不同的对象

1

	public class Main {
	    public static void main(String[] args) {
	        String str1 = "hello world";
	        String str2 = new String("hello world");
	        String str3 = "hello world";
	        String str4 = new String("hello world");
	         
	        System.out.println(str1==str2);//false
	        System.out.println(str1==str3);//true
	        System.out.println(str2==str4);//false
	    }
	}

2 String str = new String("abc")创建了多少个对象？

很显然，new只调用了一次，也就是说只创建了一个对象。

在运行期间确实只在堆上创建了一个对象。

为什么大家都在说是2个对象呢？在类加载的过程中，确实在运行时常量池中创建了一个"abc"对象。

因此，这个问题如果换成 String str = new String("abc")涉及到几个String对象？合理的解释是2个。

## 常量池、编译期常量优化 ##

**class文件常量池** 

- 存储编译期间生成的 字面常量以及符号引用，在运行期间对应着方法区的运行时常量池。
- 编译期间常量优化。
	- 字符串直接相加，优化。
		- 把相加结果为一个常量字符串存入class文件常量池
	- 字符串间接相加(即包含字符串引用)
		- 引用非final，不优化。 
			- 因为b+2这种方式生成的对象事实上是保存在堆上的
		- 引用final
			- 引用值是字面常量值，优化。 
				- 因为final变量编译期间都会直接被替代为真实的字面常量值，并将该字面常量值存入class文件常量池
			- 引用值非字面常量值(如方法返回值)，不优化。 
				- 因为值只能在运行期间确定
		


1

	String a = "hello2";
	String b = "hello" + 2;//直接相加，优化
	System.out.println((a == b));//true

2
	
	String a = "hello2";
	String b = "hello";
	String c = b + 2;//间接相加,引用非final，不优化
	System.out.println((a == c));//false
	
3

	String a = "hello2";   　 
	final String b = "hello";       
	String c = b + 2;    //间接相加,引用final且引用值是常量值，优化   
	System.out.println((a == c));//true

4
	
	public class Main {
	    public static void main(String[] args) {
	        String a = "hello2";
	        final String b = getHello();
	        String c = b + 2;//间接相加,引用final且引用值非常量值，不优化   
	        System.out.println((a == c));//false
	    }
	     
	    public static String getHello() {
	        return "hello";
	    }
	}

## intern()方法 ##

String类的intern方法是一个**本地方法**。**只会直接访问运行时常量池**

JDK1.6，intern方法会在运行时常量池中查找是否存在内容相同的字符串，如果存在则返回指向该字符串的引用，如果不存在，则会将该字符串入池，并返回一个指向该字符串的引用。

	public class Main {
	    public static void main(String[] args) {
	        String a = "hello";
	        String b =  new String("hello");
	        String c =  new String("hello");
	        String d = b.intern();
	         
	        System.out.println(a==b);//false
	        System.out.println(b==c);//false
	        System.out.println(b==d);//false
	        System.out.println(a==d);//true
	    }
	}

# StringBuilder #

	public class Main {
	    public static void main(String[] args) {
	        String string = "";
	        for(int i=0;i<10000;i++){
	            string += "hello";
	        }
	    }
	}


反编译字节码：
	
	  public static void main(java.lang.String[]);
	    Code:
	       0: ldc           #2                  // String
	       2: astore_1
	       3: iconst_0
	       4: istore_2
	       5: iload_2
	       6: sipush        10000
	       9: if_icmpge     38
	      12: new           #3                  // class java/lang/StringBuilder
	      15: dup
	      16: invokespecial #4                  // Method java/lang/StringBuilder."<init>":()V
	      19: aload_1
	      20: invokevirtual #5                  // Method java/lang/StringBuilder.append:(Ljava/lang/String;)Ljava/lang/Stri
	ngBuilder;
	      23: ldc           #6                  // String hello
	      25: invokevirtual #5                  // Method java/lang/StringBuilder.append:(Ljava/lang/String;)Ljava/lang/Stri
	ngBuilder;
	      28: invokevirtual #7                  // Method java/lang/StringBuilder.toString:()Ljava/lang/String;
	      31: astore_1
	      32: iinc          2, 1
	      35: goto          5
	      38: return

string += "hello";的过程相当于将原有的string变量指向的对象内容取出与"hello"作字符串相加操作再存进另一个新的String对象当中，再让string变量指向新生成的对象

从第5行到第35行是整个循环的执行过程，每次循环会new出一个StringBuilder对象，然后进行append操作，最后通过toString方法返回String对象。循环new出了10000个对象。从上面还可以看出：string+="hello"的操作事实上会自动被JVM优化成：
	
	StringBuilder str = new StringBuilder(string);
	str.append("hello");
	str.toString();

# StringBuffer #

**线程安全**

StringBuffer类的成员方法前面多了一个关键字：synchronized

# 效率 #

从高到低，依次为：

**直接相加**

- 效率最高，因为在编译期间优化了，便确定了它的值

		String s = "I"+"love"+"java";//在编译期间便被优化成了"Ilovejava"

**StringBuilder**

**StringBuffer**

**间接相加(即包含字符串引用)**

- 效率特别低，因为在编译器不会对引用变量进行优化。形如s1+s2+s3; 

		String s1 ="I";
		String s2 = "love";
		String s3 = "java";
		String s = s1+s2+s3;
